hack4u/__init__.py
hack4u/courses.py
hack4u/utils.py
THack4u-0.1.0.dist-info/METADATA
THack4u-0.1.0.dist-info/WHEEL
THack4u-0.1.0.dist-info/top_level.txt
THack4u-0.1.0.dist-info/RECORD
